{
    "date_time": "2023-10-23T12:21:53.703083",
    "base": "USD",
    "rates": {
        "AED": 3.67301,
        "AFN": 75.384194,
        "ALL": 99.857374,
        "AMD": 401.715295,
        "ANG": 1.80191,
        "AOA": 829.504567,
        "ARS": 349.818398,
        "AUD": 1.58577,
        "AWG": 1.8,
        "AZN": 1.700677,
        "BAM": 1.847343,
        "BBD": 2.018778,
        "BDT": 110.237931,
        "BGN": 1.84514,
        "BHD": 0.377031,
        "BIF": 2837.698066,
        "BMD": 1,
        "BND": 1.372187,
        "BOB": 6.908407,
        "BRL": 5.033296,
        "BSD": 0.999802,
        "BTC": 3.2706288e-05,
        "BTN": 83.112171,
        "BWP": 13.752326,
        "BYN": 3.293536,
        "BYR": 19600,
        "BZD": 2.015377,
        "CAD": 1.371049,
        "CDF": 2555.00009,
        "CHF": 0.892901,
        "CLF": 0.034234,
        "CLP": 944.629654,
        "CNY": 7.3163,
        "COP": 4236,
        "CRC": 530.74024,
        "CUC": 1,
        "CUP": 26.5,
        "CVE": 104.150334,
        "CZK": 23.231801,
        "DJF": 178.018532,
        "DKK": 7.03293,
        "DOP": 56.861652,
        "DZD": 137.384984,
        "EGP": 30.924502,
        "ERN": 15,
        "ETB": 55.412719,
        "EUR": 0.942397,
        "FJD": 2.28945,
        "FKP": 0.822414,
        "GBP": 0.82176,
        "GEL": 2.695029,
        "GGP": 0.822414,
        "GHS": 11.768095,
        "GIP": 0.822414,
        "GMD": 65.624975,
        "GNF": 8588.835364,
        "GTQ": 7.825923,
        "GYD": 209.396341,
        "HKD": 7.826215,
        "HNL": 24.676257,
        "HRK": 7.168957,
        "HTG": 133.477538,
        "HUF": 359.810506,
        "IDR": 15926,
        "ILS": 4.06001,
        "IMP": 0.822414,
        "INR": 83.166901,
        "IQD": 1309.801551,
        "IRR": 42250.000199,
        "ISK": 138.439726,
        "JEP": 0.822414,
        "JMD": 154.990507,
        "JOD": 0.709198,
        "JPY": 149.930504,
        "KES": 150.101353,
        "KGS": 89.319845,
        "KHR": 4131.560056,
        "KMF": 464.628417,
        "KPW": 899.999897,
        "KRW": 1352.3799,
        "KWD": 0.30916,
        "KYD": 0.833184,
        "KZT": 479.441962,
        "LAK": 20701.608561,
        "LBP": 15027.344599,
        "LKR": 325.452674,
        "LRD": 186.999982,
        "LSL": 19.000076,
        "LTL": 2.95274,
        "LVL": 0.60489,
        "LYD": 4.89747,
        "MAD": 10.290353,
        "MDL": 18.207365,
        "MGA": 4529.011174,
        "MKD": 58.253207,
        "MMK": 2099.630683,
        "MNT": 3454.596776,
        "MOP": 8.043095,
        "MRO": 356.999828,
        "MUR": 44.368392,
        "MVR": 15.406428,
        "MWK": 1155.746144,
        "MXN": 18.30879,
        "MYR": 4.788901,
        "MZN": 63.24995,
        "NAD": 18.999755,
        "NGN": 859.730137,
        "NIO": 36.522231,
        "NOK": 11.116502,
        "NPR": 132.972202,
        "NZD": 1.71831,
        "OMR": 0.38493,
        "PAB": 0.999802,
        "PEN": 3.870465,
        "PGK": 3.713009,
        "PHP": 56.874503,
        "PKR": 275.449316,
        "PLN": 4.200305,
        "PYG": 7420.351182,
        "QAR": 3.641033,
        "RON": 4.685945,
        "RSD": 110.438989,
        "RUB": 94.282496,
        "RWF": 1221.203162,
        "SAR": 3.751214,
        "SBD": 8.404697,
        "SCR": 13.358601,
        "SDG": 598.712526,
        "SEK": 11.00874,
        "SGD": 1.37236,
        "SHP": 1.21675,
        "SLE": 22.635094,
        "SLL": 19750.000429,
        "SOS": 570.494531,
        "SSP": 601.000056,
        "SRD": 38.368497,
        "STD": 20697.981008,
        "SYP": 13001.855133,
        "SZL": 19.084366,
        "THB": 36.454031,
        "TJS": 10.973693,
        "TMT": 3.5,
        "TND": 3.16625,
        "TOP": 2.40545,
        "TRY": 28.051007,
        "TTD": 6.791284,
        "TWD": 32.376498,
        "TZS": 2501.000617,
        "UAH": 36.523599,
        "UGX": 3752.680148,
        "USD": 1,
        "UYU": 39.899872,
        "UZS": 12208.967891,
        "VEF": 3477655.031224,
        "VES": 34.814855,
        "VND": 24610,
        "VUV": 122.129972,
        "WST": 2.80427,
        "XAF": 619.581377,
        "XAG": 0.043024,
        "XAU": 0.000505,
        "XCD": 2.70255,
        "XDR": 0.76299,
        "XOF": 619.581377,
        "XPF": 112.908989,
        "YER": 250.324985,
        "ZAR": 19.10086,
        "ZMK": 9001.202416,
        "ZMW": 21.565373,
        "ZWL": 321.999592
    }
}